distill_trainer/__init__.py
distill_trainer/benchmark.py
distill_trainer/data/process.py
distill_trainer/data/s3.py
distill_trainer/trainer.py
distill_trainer-0.1.1.dist-info/METADATA
distill_trainer-0.1.1.dist-info/WHEEL
distill_trainer-0.1.1.dist-info/RECORD
