Metadata-Version: 2.1
Name: distill-trainer
Version: 0.1.1
Summary: Knowledge distillation toolkit
Author: pagarsky
Author-email: oleksii.paharskyi@gmail.com
Requires-Python: >=3.8,<4.0
Classifier: Programming Language :: Python :: 3
Classifier: Programming Language :: Python :: 3.8
Classifier: Programming Language :: Python :: 3.9
Classifier: Programming Language :: Python :: 3.10
Classifier: Programming Language :: Python :: 3.11
Requires-Dist: aiohttp (==3.8.4)
Requires-Dist: aiosignal (==1.3.1)
Requires-Dist: async-timeout (==4.0.2)
Requires-Dist: attrs (==23.1.0)
Requires-Dist: boto3 (==1.26.142)
Requires-Dist: botocore (==1.29.142)
Requires-Dist: build (==0.10.0)
Requires-Dist: cachecontrol (==0.12.11)
Requires-Dist: certifi (==2023.5.7)
Requires-Dist: cffi (==1.15.1)
Requires-Dist: charset-normalizer (==3.1.0)
Requires-Dist: cleo (==2.0.1)
Requires-Dist: crashtest (==0.4.1)
Requires-Dist: datasets (==2.12.0)
Requires-Dist: dill (==0.3.6)
Requires-Dist: distlib (==0.3.6)
Requires-Dist: dulwich (==0.21.5)
Requires-Dist: filelock (==3.12.0)
Requires-Dist: frozenlist (==1.3.3)
Requires-Dist: fsspec (==2023.5.0)
Requires-Dist: html5lib (==1.1)
Requires-Dist: huggingface-hub (==0.14.1)
Requires-Dist: idna (==3.4)
Requires-Dist: importlib-metadata (==6.6.0)
Requires-Dist: installer (==0.7.0)
Requires-Dist: jaraco-classes (==3.2.3)
Requires-Dist: jinja2 (==3.1.2)
Requires-Dist: jmespath (==1.0.1)
Requires-Dist: jsonschema (==4.17.3)
Requires-Dist: keyring (==23.13.1)
Requires-Dist: lockfile (==0.12.2)
Requires-Dist: markupsafe (==2.1.2)
Requires-Dist: more-itertools (==9.1.0)
Requires-Dist: mpmath (==1.3.0)
Requires-Dist: msgpack (==1.0.5)
Requires-Dist: multidict (==6.0.4)
Requires-Dist: multiprocess (==0.70.14)
Requires-Dist: networkx (==3.1)
Requires-Dist: numpy (==1.24.3)
Requires-Dist: packaging (==23.1)
Requires-Dist: pandas (==2.0.1)
Requires-Dist: pexpect (==4.8.0)
Requires-Dist: pkginfo (==1.9.6)
Requires-Dist: platformdirs (==3.5.1)
Requires-Dist: poetry (==1.5.0)
Requires-Dist: poetry-core (==1.6.0)
Requires-Dist: poetry-plugin-export (==1.3.1)
Requires-Dist: ptyprocess (==0.7.0)
Requires-Dist: pyarrow (==12.0.0)
Requires-Dist: pycparser (==2.21)
Requires-Dist: pyproject-hooks (==1.0.0)
Requires-Dist: pyrsistent (==0.19.3)
Requires-Dist: python-dateutil (==2.8.2)
Requires-Dist: pytz (==2023.3)
Requires-Dist: pyyaml (==6.0)
Requires-Dist: rapidfuzz (==2.15.1)
Requires-Dist: regex (==2023.5.5)
Requires-Dist: requests (==2.31.0)
Requires-Dist: requests-toolbelt (==1.0.0)
Requires-Dist: responses (==0.18.0)
Requires-Dist: s3transfer (==0.6.1)
Requires-Dist: shellingham (==1.5.0.post1)
Requires-Dist: six (==1.16.0)
Requires-Dist: sympy (==1.12)
Requires-Dist: tokenizers (==0.13.3)
Requires-Dist: tomlkit (==0.11.8)
Requires-Dist: torch (==2.0.1)
Requires-Dist: tqdm (==4.65.0)
Requires-Dist: transformers (==4.29.2)
Requires-Dist: trove-classifiers (==2023.5.24)
Requires-Dist: typing-extensions (==4.6.2)
Requires-Dist: tzdata (==2023.3)
Requires-Dist: urllib3 (==1.26.16)
Requires-Dist: virtualenv (==20.23.0)
Requires-Dist: webencodings (==0.5.1)
Requires-Dist: xattr (==0.10.1)
Requires-Dist: xxhash (==3.2.0)
Requires-Dist: yarl (==1.9.2)
Requires-Dist: zipp (==3.15.0)
